acouchbase_analytics/__init__.py
acouchbase_analytics/cluster.py
acouchbase_analytics/cluster.pyi
acouchbase_analytics/credential.py
acouchbase_analytics/database.py
acouchbase_analytics/database.pyi
acouchbase_analytics/deserializer.py
acouchbase_analytics/errors.py
acouchbase_analytics/options.py
acouchbase_analytics/query.py
acouchbase_analytics/result.py
acouchbase_analytics/scope.py
acouchbase_analytics/scope.pyi
acouchbase_analytics/protocol/__init__.py
acouchbase_analytics/protocol/cluster.py
acouchbase_analytics/protocol/cluster.pyi
acouchbase_analytics/protocol/database.py
acouchbase_analytics/protocol/database.pyi
acouchbase_analytics/protocol/errors.py
acouchbase_analytics/protocol/scope.py
acouchbase_analytics/protocol/scope.pyi
acouchbase_analytics/protocol/streaming.py
acouchbase_analytics/protocol/_core/__init__.py
acouchbase_analytics/protocol/_core/anyio_utils.py
acouchbase_analytics/protocol/_core/async_json_stream.py
acouchbase_analytics/protocol/_core/async_json_token_parser.py
acouchbase_analytics/protocol/_core/client_adapter.py
acouchbase_analytics/protocol/_core/net_utils.py
acouchbase_analytics/protocol/_core/request_context.py
acouchbase_analytics/protocol/_core/retries.py
couchbase_analytics/__init__.py
couchbase_analytics/_version.py
couchbase_analytics/cluster.py
couchbase_analytics/cluster.pyi
couchbase_analytics/credential.py
couchbase_analytics/database.py
couchbase_analytics/database.pyi
couchbase_analytics/deserializer.py
couchbase_analytics/errors.py
couchbase_analytics/options.py
couchbase_analytics/query.py
couchbase_analytics/result.py
couchbase_analytics/scope.py
couchbase_analytics/scope.pyi
couchbase_analytics/common/__init__.py
couchbase_analytics/common/backoff_calculator.py
couchbase_analytics/common/credential.py
couchbase_analytics/common/deserializer.py
couchbase_analytics/common/enums.py
couchbase_analytics/common/errors.py
couchbase_analytics/common/logging.py
couchbase_analytics/common/options.py
couchbase_analytics-1.0.0.dist-info/licenses/LICENSE
couchbase_analytics-1.0.0.dist-info/METADATA
couchbase_analytics-1.0.0.dist-info/WHEEL
couchbase_analytics-1.0.0.dist-info/top_level.txt
couchbase_analytics-1.0.0.dist-info/RECORD
