Metadata-Version: 2.4
Name: couchbase-analytics
Version: 1.0.0
Summary: Python Client for Couchbase Analytics
Author-email: "Couchbase, Inc." <PythonPackage@couchbase.com>
Maintainer-email: "Couchbase, Inc." <PythonPackage@couchbase.com>
Project-URL: Homepage, https://couchbase.com
Project-URL: Documentation, https://docs.couchbase.com/python-analytics-sdk/current/hello-world/overview.html
Project-URL: API Reference, https://docs.couchbase.com/sdk-api/analytics-python-client/
Project-URL: Repository, https://github.com/couchbase/analytics-python-client
Project-URL: Bug Tracker, https://issues.couchbase.com/projects/PYCO/issues/
Project-URL: Release Notes, https://docs.couchbase.com/python-analytics-sdk/current/project-docs/analytics-sdk-release-notes.html
Keywords: couchbase,nosql,pycouchbase,couchbase++,analytics
Classifier: Development Status :: 4 - Beta
Classifier: Intended Audience :: Developers
Classifier: License :: OSI Approved :: Apache Software License
Classifier: Operating System :: OS Independent
Classifier: Programming Language :: Python :: 3
Classifier: Programming Language :: Python :: 3.9
Classifier: Programming Language :: Python :: 3.10
Classifier: Programming Language :: Python :: 3.11
Classifier: Programming Language :: Python :: 3.12
Classifier: Programming Language :: Python :: 3.13
Classifier: Programming Language :: Python :: Implementation :: CPython
Classifier: Topic :: Database
Classifier: Topic :: Software Development :: Libraries
Classifier: Topic :: Software Development :: Libraries :: Python Modules
Requires-Python: >=3.9
License-File: LICENSE
Requires-Dist: anyio~=4.9.0
Requires-Dist: httpx~=0.28.1
Requires-Dist: ijson~=3.4.0
Requires-Dist: sniffio~=1.3.1
Requires-Dist: typing-extensions~=4.11; python_version < "3.11"
Dynamic: license-file
